{
        "custom": {
                "host": "smtp.gmail.com",
                "port": 25,
                "ignoreTLS": true,
                "debug": true,
                "logger": true,
                "secure": false,
                "auth": {
                        "user": "help@example.com",
                        "pass": "password"
                }
        },
        "unsecure": {
                "host": "smtp.gmail.com",
                "port": 25,
                "debug": true,
                "logger": true,
                "secure": false,
                "auth": {
                        "user": "help@example.com",
                        "pass": "password"
                }
        },
        "secure": {
                "host": "smtp.gmail.com",
                "port": 465,
                "debug": true,
                "logger": true,
                "secure": true,
                "auth": {
                        "user": "help@example.com",
                        "pass": "password"
                }
        },
        "emailcontent": {
                "from": ["Support <help@example.com>"],
                "to": ["help@example.com"],
                "subject": [" - do not delete this email"],
                "text": ["DO NOT DELETE or REPLY TO THIS EMAIL"],
                "html": ["<b><p> DO NOT DELETE or REPLY TO THIS EMAIL  </p> <p> Regards </p> <p> Test </p></b>"]
        }
}
